[
  {
    "id": 87600005,
    "idCN": "深渊/01期/深渊01",
    "mod": "默认",
    "isInformalData": false,
    "abyssName": "止火破阵·一",
    "abyssDes": "",
    "abyssPeriodId": 87700001,
    "levelList": [
      {
        "id": 20100961,
        "spinePosX": 0.0,
        "spinePosY": -180.0,
        "spineScale": 0.9
      },
      {
        "id": 20100964,
        "spinePosX": 0.0,
        "spinePosY": -180.0,
        "spineScale": 0.9
      }
    ],
    "firstPassAward": [],
    "firstPassAwardS": [],
    "timeStar": 720
  },
  {
    "id": 87600006,
    "idCN": "深渊/01期/深渊02",
    "mod": "默认",
    "isInformalData": false,
    "abyssName": "止火破阵·二",
    "abyssDes": "",
    "abyssIndex": "RS-02",
    "abyssPeriodId": 87700001,
    "levelList": [
      {
        "id": 20100967,
        "spinePosX": 0.0,
        "spinePosY": -180.0,
        "spineScale": 0.9
      },
      {
        "id": 20100971,
        "spinePosX": 0.0,
        "spinePosY": -180.0,
        "spineScale": 0.9
      }
    ],
    "firstPassAward": [],
    "firstPassAwardS": [],
    "timeStar": 720
  },
  {
    "id": 87600007,
    "idCN": "深渊/01期/深渊03",
    "mod": "默认",
    "isInformalData": false,
    "abyssName": "止火破阵·三",
    "abyssDes": "",
    "abyssIndex": "RS-03",
    "abyssPeriodId": 87700001,
    "levelList": [
      {
        "id": 20100968,
        "spinePosX": 0.0,
        "spinePosY": -180.0,
        "spineScale": 0.9
      },
      {
        "id": 20100972,
        "spinePosX": 0.0,
        "spinePosY": -180.0,
        "spineScale": 0.9
      }
    ],
    "firstPassAward": [],
    "firstPassAwardS": [],
    "timeStar": 720
  },
  {
    "id": 87600008,
    "idCN": "深渊/01期/深渊04",
    "mod": "默认",
    "isInformalData": false,
    "abyssName": "止火破阵·四",
    "abyssDes": "",
    "abyssIndex": "RS-04",
    "abyssPeriodId": 87700001,
    "levelList": [
      {
        "id": 20100969,
        "spinePosX": 0.0,
        "spinePosY": -180.0,
        "spineScale": 0.9
      },
      {
        "id": 20100973,
        "spinePosX": 0.0,
        "spinePosY": -180.0,
        "spineScale": 0.9
      }
    ],
    "firstPassAward": [],
    "firstPassAwardS": [],
    "timeStar": 720
  },
  {
    "id": 87600001,
    "idCN": "深渊/02期/深渊02",
    "mod": "默认",
    "isInformalData": false,
    "abyssName": "凝雪扬沙·二",
    "abyssDes": "",
    "abyssIndex": "BW-02",
    "abyssPeriodId": 87700003,
    "levelList": [
      {
        "id": 20101067,
        "spinePosX": 48.0,
        "spinePosY": -274.0,
        "spineScale": 0.9
      },
      {
        "id": 20101060,
        "spinePosX": 0.0,
        "spinePosY": -180.0,
        "spineScale": 0.9
      }
    ],
    "firstPassAward": [],
    "firstPassAwardS": [],
    "timeStar": 720
  },
  {
    "id": 87600002,
    "idCN": "深渊/02期/深渊01",
    "mod": "默认",
    "isInformalData": false,
    "abyssName": "凝雪扬沙·一",
    "abyssDes": "",
    "abyssIndex": "BW-01",
    "abyssPeriodId": 87700003,
    "levelList": [
      {
        "id": 20101063,
        "spinePosX": 48.0,
        "spinePosY": -274.0,
        "spineScale": 0.9
      },
      {
        "id": 20101070,
        "spinePosX": 0.0,
        "spinePosY": -180.0,
        "spineScale": 0.9
      }
    ],
    "firstPassAward": [],
    "firstPassAwardS": [],
    "timeStar": 720
  },
  {
    "id": 87600003,
    "idCN": "深渊/02期/深渊03",
    "mod": "默认",
    "isInformalData": false,
    "abyssName": "凝雪扬沙·三",
    "abyssDes": "",
    "abyssIndex": "BW-03",
    "abyssPeriodId": 87700003,
    "levelList": [
      {
        "id": 20101062,
        "spinePosX": 48.0,
        "spinePosY": -274.0,
        "spineScale": 0.9
      },
      {
        "id": 20101061,
        "spinePosX": 0.0,
        "spinePosY": -180.0,
        "spineScale": 0.9
      }
    ],
    "firstPassAward": [],
    "firstPassAwardS": [],
    "timeStar": 720
  },
  {
    "id": 87600004,
    "idCN": "深渊/02期/深渊04",
    "mod": "默认",
    "isInformalData": false,
    "abyssName": "凝雪扬沙·四",
    "abyssDes": "",
    "abyssIndex": "BW-04",
    "abyssPeriodId": 87700003,
    "levelList": [
      {
        "id": 20101071,
        "spinePosX": 48.0,
        "spinePosY": -274.0,
        "spineScale": 0.9
      },
      {
        "id": 20101068,
        "spinePosX": 0.0,
        "spinePosY": -180.0,
        "spineScale": 0.9
      }
    ],
    "firstPassAward": [],
    "firstPassAwardS": [],
    "timeStar": 720
  },
  {
    "id": 87600009,
    "idCN": "深渊/03期/深渊03",
    "mod": "默认",
    "isInformalData": false,
    "abyssName": "淘金传奇·三",
    "abyssDes": "",
    "abyssIndex": "MS-03",
    "abyssPeriodId": 87700002,
    "levelList": [
      {
        "id": 20101105,
        "spinePosX": 0.0,
        "spinePosY": -100.0,
        "spineScale": 1.0
      },
      {
        "id": 20101102,
        "spinePosX": 0.0,
        "spinePosY": -100.0,
        "spineScale": 1.0
      }
    ],
    "firstPassAward": [],
    "firstPassAwardS": [],
    "timeStar": 720
  },
  {
    "id": 87600010,
    "idCN": "深渊/03期/深渊01",
    "mod": "默认",
    "isInformalData": false,
    "abyssName": "淘金传奇·一",
    "abyssDes": "",
    "abyssIndex": "MS-01",
    "abyssPeriodId": 87700002,
    "levelList": [
      {
        "id": 20101106,
        "spinePosX": 0.0,
        "spinePosY": -100.0,
        "spineScale": 1.0
      },
      {
        "id": 20101100,
        "spinePosX": 0.0,
        "spinePosY": -100.0,
        "spineScale": 1.0
      }
    ],
    "firstPassAward": [],
    "firstPassAwardS": [],
    "timeStar": 720
  },
  {
    "id": 87600011,
    "idCN": "深渊/03期/深渊04",
    "mod": "默认",
    "isInformalData": false,
    "abyssName": "淘金传奇·四",
    "abyssDes": "",
    "abyssIndex": "MS-04",
    "abyssPeriodId": 87700002,
    "levelList": [
      {
        "id": 20101103,
        "spinePosX": 0.0,
        "spinePosY": -100.0,
        "spineScale": 1.0
      },
      {
        "id": 20101107,
        "spinePosX": 0.0,
        "spinePosY": -100.0,
        "spineScale": 1.0
      }
    ],
    "firstPassAward": [],
    "firstPassAwardS": [],
    "timeStar": 720
  },
  {
    "id": 87600012,
    "idCN": "深渊/03期/深渊02",
    "mod": "默认",
    "isInformalData": false,
    "abyssName": "淘金传奇·二",
    "abyssDes": "",
    "abyssIndex": "MS-02",
    "abyssPeriodId": 87700002,
    "levelList": [
      {
        "id": 20101101,
        "spinePosX": 0.0,
        "spinePosY": -100.0,
        "spineScale": 1.0
      },
      {
        "id": 20101104,
        "spinePosX": 0.0,
        "spinePosY": -100.0,
        "spineScale": 1.0
      }
    ],
    "firstPassAward": [],
    "firstPassAwardS": [],
    "timeStar": 720
  },
  {
    "id": 87600013,
    "idCN": "打劫事件/测试",
    "mod": "默认",
    "isInformalData": false,
    "abyssName": "止火破阵·一",
    "abyssDes": "",
    "abyssIndex": "RS-01",
    "abyssPeriodId": -1,
    "levelList": [
      {
        "id": 20100961,
        "spinePosX": 0.0,
        "spinePosY": -180.0,
        "spineScale": 0.9
      },
      {
        "id": 20100964,
        "spinePosX": 0.0,
        "spinePosY": -180.0,
        "spineScale": 0.9
      }
    ],
    "firstPassAward": [],
    "firstPassAwardS": [],
    "timeStar": 720
  },
  {
    "id": 87600014,
    "idCN": "深渊/04期/深渊03",
    "mod": "默认",
    "isInformalData": false,
    "abyssName": "昏天黑地·三",
    "abyssDes": "",
    "abyssIndex": "HE-03",
    "abyssPeriodId": 87700004,
    "levelList": [
      {
        "id": 20101132,
        "spinePosX": 0.0,
        "spinePosY": -165.0,
        "spineScale": 0.7
      },
      {
        "id": 20101131,
        "spinePosX": 0.0,
        "spinePosY": -180.0,
        "spineScale": 0.7
      }
    ],
    "firstPassAward": [],
    "firstPassAwardS": [],
    "timeStar": 720
  },
  {
    "id": 87600015,
    "idCN": "深渊/04期/深渊01",
    "mod": "默认",
    "isInformalData": false,
    "abyssName": "昏天黑地·一",
    "abyssDes": "",
    "abyssIndex": "HE-01",
    "abyssPeriodId": 87700004,
    "levelList": [
      {
        "id": 20101138,
        "spinePosX": 0.0,
        "spinePosY": -165.0,
        "spineScale": 0.7
      },
      {
        "id": 20101136,
        "spinePosX": 0.0,
        "spinePosY": -180.0,
        "spineScale": 0.7
      }
    ],
    "firstPassAward": [],
    "firstPassAwardS": [],
    "timeStar": 720
  },
  {
    "id": 87600016,
    "idCN": "深渊/04期/深渊02",
    "mod": "默认",
    "isInformalData": false,
    "abyssName": "昏天黑地·二",
    "abyssDes": "",
    "abyssIndex": "HE-02",
    "abyssPeriodId": 87700004,
    "levelList": [
      {
        "id": 20101133,
        "spinePosX": 0.0,
        "spinePosY": -165.0,
        "spineScale": 0.7
      },
      {
        "id": 20101137,
        "spinePosX": 0.0,
        "spinePosY": -180.0,
        "spineScale": 0.7
      }
    ],
    "firstPassAward": [],
    "firstPassAwardS": [],
    "timeStar": 720
  },
  {
    "id": 87600017,
    "idCN": "深渊/04期/深渊04",
    "mod": "默认",
    "isInformalData": false,
    "abyssName": "昏天黑地·四",
    "abyssDes": "",
    "abyssIndex": "HE-04",
    "abyssPeriodId": 87700004,
    "levelList": [
      {
        "id": 20101134,
        "spinePosX": 0.0,
        "spinePosY": -165.0,
        "spineScale": 0.7
      },
      {
        "id": 20101135,
        "spinePosX": 0.0,
        "spinePosY": -180.0,
        "spineScale": 0.7
      }
    ],
    "firstPassAward": [],
    "firstPassAwardS": [],
    "timeStar": 720
  },
  {
    "id": 87600018,
    "idCN": "深渊/05期/深渊02",
    "mod": "默认",
    "isInformalData": false,
    "abyssName": "重型对抗·二",
    "abyssDes": "",
    "abyssIndex": "SL-02",
    "abyssPeriodId": 87700009,
    "levelList": [
      {
        "id": 20101159,
        "spinePosX": 0.0,
        "spinePosY": -180.0,
        "spineScale": 0.9
      },
      {
        "id": 20101163,
        "spinePosX": 0.0,
        "spinePosY": -180.0,
        "spineScale": 0.9
      }
    ],
    "firstPassAward": [],
    "firstPassAwardS": [],
    "timeStar": 720
  },
  {
    "id": 87600019,
    "idCN": "深渊/05期/深渊01",
    "mod": "默认",
    "isInformalData": false,
    "abyssName": "重型对抗·一",
    "abyssDes": "",
    "abyssIndex": "SL--01",
    "abyssPeriodId": 87700009,
    "levelList": [
      {
        "id": 20101165,
        "spinePosX": 0.0,
        "spinePosY": -180.0,
        "spineScale": 0.9
      },
      {
        "id": 20101161,
        "spinePosX": 0.0,
        "spinePosY": -180.0,
        "spineScale": 0.9
      }
    ],
    "firstPassAward": [],
    "firstPassAwardS": [],
    "timeStar": 720
  },
  {
    "id": 87600020,
    "idCN": "深渊/05期/深渊04",
    "mod": "默认",
    "isInformalData": false,
    "abyssName": "重型对抗·四",
    "abyssDes": "",
    "abyssIndex": "SL-04",
    "abyssPeriodId": 87700009,
    "levelList": [
      {
        "id": 20101162,
        "spinePosX": 0.0,
        "spinePosY": -180.0,
        "spineScale": 0.9
      },
      {
        "id": 20101160,
        "spinePosX": 0.0,
        "spinePosY": -180.0,
        "spineScale": 0.9
      }
    ],
    "firstPassAward": [],
    "firstPassAwardS": [],
    "timeStar": 720
  },
  {
    "id": 87600021,
    "idCN": "深渊/05期/深渊03",
    "mod": "默认",
    "isInformalData": false,
    "abyssName": "重型对抗·三",
    "abyssDes": "",
    "abyssIndex": "SL-03",
    "abyssPeriodId": 87700009,
    "levelList": [
      {
        "id": 20101166,
        "spinePosX": 0.0,
        "spinePosY": -180.0,
        "spineScale": 0.9
      },
      {
        "id": 20101164,
        "spinePosX": 0.0,
        "spinePosY": -180.0,
        "spineScale": 0.9
      }
    ],
    "firstPassAward": [],
    "firstPassAwardS": [],
    "timeStar": 720
  },
  {
    "id": 87600022,
    "idCN": "深渊/06期/深渊02",
    "mod": "默认",
    "isInformalData": false,
    "abyssName": "魔剑与魔女·二",
    "abyssDes": "",
    "abyssIndex": "KM-02",
    "abyssPeriodId": 87700014,
    "levelList": [
      {
        "id": 20101172,
        "spinePosX": 0.0,
        "spinePosY": -140.0,
        "spineScale": 1.0
      },
      {
        "id": 20101169,
        "spinePosX": 0.0,
        "spinePosY": -140.0,
        "spineScale": 1.0
      }
    ],
    "firstPassAward": [],
    "firstPassAwardS": [],
    "timeStar": 720
  },
  {
    "id": 87600023,
    "idCN": "深渊/06期/深渊01",
    "mod": "默认",
    "isInformalData": false,
    "abyssName": "魔剑与魔女·一",
    "abyssDes": "",
    "abyssIndex": "KM-01",
    "abyssPeriodId": 87700014,
    "levelList": [
      {
        "id": 20101120,
        "spinePosX": 0.0,
        "spinePosY": -140.0,
        "spineScale": 1.0
      },
      {
        "id": 20101174,
        "spinePosX": 0.0,
        "spinePosY": -140.0,
        "spineScale": 1.0
      }
    ],
    "firstPassAward": [],
    "firstPassAwardS": [],
    "timeStar": 720
  },
  {
    "id": 87600024,
    "idCN": "深渊/06期/深渊04",
    "mod": "默认",
    "isInformalData": false,
    "abyssName": "魔剑与魔女·四",
    "abyssDes": "",
    "abyssIndex": "KM-04",
    "abyssPeriodId": 87700014,
    "levelList": [
      {
        "id": 20101175,
        "spinePosX": 0.0,
        "spinePosY": -140.0,
        "spineScale": 1.0
      },
      {
        "id": 20101173,
        "spinePosX": 0.0,
        "spinePosY": -140.0,
        "spineScale": 1.0
      }
    ],
    "firstPassAward": [],
    "firstPassAwardS": [],
    "timeStar": 720
  },
  {
    "id": 87600025,
    "idCN": "深渊/06期/深渊03",
    "mod": "默认",
    "isInformalData": false,
    "abyssName": "魔剑与魔女·三",
    "abyssDes": "",
    "abyssIndex": "KM-03",
    "abyssPeriodId": 87700014,
    "levelList": [
      {
        "id": 20101170,
        "spinePosX": 0.0,
        "spinePosY": -140.0,
        "spineScale": 1.0
      },
      {
        "id": 20101171,
        "spinePosX": 0.0,
        "spinePosY": -140.0,
        "spineScale": 1.0
      }
    ],
    "firstPassAward": [],
    "firstPassAwardS": [],
    "timeStar": 720
  },
  {
    "id": 87600027,
    "idCN": "作战中心/汇流塔/关卡01",
    "mod": "默认",
    "isInformalData": false,
    "abyssName": "入梦·上",
    "abyssDes": "",
    "abyssIndex": "HL-01",
    "abyssPeriodId": -1,
    "levelList": [
      {
        "id": 20101127,
        "spinePosX": 0.0,
        "spinePosY": -180.0,
        "spineScale": 0.9
      },
      {
        "id": 20101193,
        "spinePosX": 0.0,
        "spinePosY": -180.0,
        "spineScale": 0.9
      }
    ],
    "firstPassAward": [],
    "firstPassAwardS": [],
    "timeStar": 720
  },
  {
    "id": 87600028,
    "idCN": "作战中心/汇流塔/关卡02",
    "mod": "默认",
    "isInformalData": false,
    "abyssName": "入梦·下",
    "abyssDes": "",
    "abyssIndex": "HL-02",
    "abyssPeriodId": -1,
    "levelList": [
      {
        "id": 20101184,
        "spinePosX": 0.0,
        "spinePosY": -180.0,
        "spineScale": 0.9
      },
      {
        "id": 20101194,
        "spinePosX": 0.0,
        "spinePosY": -180.0,
        "spineScale": 0.9
      }
    ],
    "firstPassAward": [],
    "firstPassAwardS": [],
    "timeStar": 720
  },
  {
    "id": 87600029,
    "idCN": "作战中心/汇流塔/关卡03",
    "mod": "默认",
    "isInformalData": false,
    "abyssName": "梦之囚徒",
    "abyssDes": "",
    "abyssIndex": "HL-03",
    "abyssPeriodId": -1,
    "levelList": [
      {
        "id": 20101185,
        "spinePosX": 0.0,
        "spinePosY": -310.0,
        "spineScale": 1.0
      },
      {
        "id": 20101195,
        "spinePosX": 0.0,
        "spinePosY": -320.0,
        "spineScale": 1.0
      }
    ],
    "firstPassAward": [],
    "firstPassAwardS": [],
    "timeStar": 720
  },
  {
    "id": 87600030,
    "idCN": "作战中心/汇流塔/关卡04",
    "mod": "默认",
    "isInformalData": false,
    "abyssName": "雷霆波涛·上",
    "abyssDes": "",
    "abyssIndex": "HL-04",
    "abyssPeriodId": -1,
    "levelList": [
      {
        "id": 20101186,
        "spinePosX": 0.0,
        "spinePosY": -220.0,
        "spineScale": 0.9
      },
      {
        "id": 20101196,
        "spinePosX": 0.0,
        "spinePosY": -180.0,
        "spineScale": 0.9
      }
    ],
    "firstPassAward": [],
    "firstPassAwardS": [],
    "timeStar": 720
  },
  {
    "id": 87600031,
    "idCN": "作战中心/汇流塔/关卡05",
    "mod": "默认",
    "isInformalData": false,
    "abyssName": "雷霆波涛·下",
    "abyssDes": "",
    "abyssIndex": "HL-05",
    "abyssPeriodId": -1,
    "levelList": [
      {
        "id": 20101187,
        "spinePosX": 0.0,
        "spinePosY": -220.0,
        "spineScale": 0.9
      },
      {
        "id": 20101197,
        "spinePosX": 0.0,
        "spinePosY": -180.0,
        "spineScale": 0.9
      }
    ],
    "firstPassAward": [],
    "firstPassAwardS": [],
    "timeStar": 720
  },
  {
    "id": 87600032,
    "idCN": "作战中心/汇流塔/关卡06",
    "mod": "默认",
    "isInformalData": false,
    "abyssName": "惊雷怒海",
    "abyssDes": "",
    "abyssIndex": "HL-06",
    "abyssPeriodId": -1,
    "levelList": [
      {
        "id": 20101188,
        "spinePosX": 0.0,
        "spinePosY": -290.0,
        "spineScale": 0.9
      },
      {
        "id": 20101198,
        "spinePosX": -55.0,
        "spinePosY": -300.0,
        "spineScale": 0.9
      }
    ],
    "firstPassAward": [],
    "firstPassAwardS": [],
    "timeStar": 720
  },
  {
    "id": 87600033,
    "idCN": "作战中心/汇流塔/关卡07",
    "mod": "默认",
    "isInformalData": false,
    "abyssName": "持火者·上",
    "abyssDes": "",
    "abyssIndex": "HL-07",
    "abyssPeriodId": -1,
    "levelList": [
      {
        "id": 20101189,
        "spinePosX": 0.0,
        "spinePosY": -140.0,
        "spineScale": 1.0
      },
      {
        "id": 20101199,
        "spinePosX": 0.0,
        "spinePosY": -140.0,
        "spineScale": 1.0
      }
    ],
    "firstPassAward": [],
    "firstPassAwardS": [],
    "timeStar": 720
  },
  {
    "id": 87600034,
    "idCN": "作战中心/汇流塔/关卡08",
    "mod": "默认",
    "isInformalData": false,
    "abyssName": "持火者·下",
    "abyssDes": "",
    "abyssIndex": "HL-08",
    "abyssPeriodId": -1,
    "levelList": [
      {
        "id": 20101190,
        "spinePosX": 0.0,
        "spinePosY": -180.0,
        "spineScale": 0.9
      },
      {
        "id": 20101200,
        "spinePosX": 0.0,
        "spinePosY": -140.0,
        "spineScale": 1.0
      }
    ],
    "firstPassAward": [],
    "firstPassAwardS": [],
    "timeStar": 720
  },
  {
    "id": 87600035,
    "idCN": "作战中心/汇流塔/关卡09",
    "mod": "默认",
    "isInformalData": false,
    "abyssName": "双重审判",
    "abyssDes": "",
    "abyssIndex": "HL-09",
    "abyssPeriodId": -1,
    "levelList": [
      {
        "id": 20101191,
        "spinePosX": 0.0,
        "spinePosY": -140.0,
        "spineScale": 1.0
      },
      {
        "id": 20101201,
        "spinePosX": 0.0,
        "spinePosY": -140.0,
        "spineScale": 1.0
      }
    ],
    "firstPassAward": [],
    "firstPassAwardS": [],
    "timeStar": 720
  },
  {
    "id": 87600036,
    "idCN": "作战中心/汇流塔/关卡10",
    "mod": "默认",
    "isInformalData": false,
    "abyssName": "奇想与学识",
    "abyssDes": "",
    "abyssIndex": "HL-10",
    "abyssPeriodId": -1,
    "levelList": [
      {
        "id": 20101192,
        "spinePosX": 0.0,
        "spinePosY": -140.0,
        "spineScale": 1.0
      },
      {
        "id": 20101202,
        "spinePosX": 0.0,
        "spinePosY": -140.0,
        "spineScale": 1.0
      }
    ],
    "firstPassAward": [],
    "firstPassAwardS": [],
    "timeStar": 720
  },
  {
    "id": 87600037,
    "idCN": "深渊/07期/深渊03",
    "mod": "默认",
    "isInformalData": false,
    "abyssName": "夺命三头龙·三",
    "abyssDes": "",
    "abyssIndex": "DT-03",
    "abyssPeriodId": 87700015,
    "levelList": [
      {
        "id": 20101216,
        "spinePosX": -55.0,
        "spinePosY": -300.0,
        "spineScale": 0.9
      },
      {
        "id": 20101209,
        "spinePosX": -55.0,
        "spinePosY": -300.0,
        "spineScale": 0.9
      }
    ],
    "firstPassAward": [],
    "firstPassAwardS": [],
    "timeStar": 720
  },
  {
    "id": 87600038,
    "idCN": "深渊/07期/深渊04",
    "mod": "默认",
    "isInformalData": false,
    "abyssName": "夺命三头龙·四",
    "abyssDes": "",
    "abyssIndex": "DT-04",
    "abyssPeriodId": 87700015,
    "levelList": [
      {
        "id": 20101211,
        "spinePosX": -55.0,
        "spinePosY": -300.0,
        "spineScale": 0.9
      },
      {
        "id": 20101210,
        "spinePosX": -55.0,
        "spinePosY": -300.0,
        "spineScale": 0.9
      }
    ],
    "firstPassAward": [],
    "firstPassAwardS": [],
    "timeStar": 720
  },
  {
    "id": 87600039,
    "idCN": "深渊/07期/深渊02",
    "mod": "默认",
    "isInformalData": false,
    "abyssName": "夺命三头龙·二",
    "abyssDes": "",
    "abyssIndex": "DT-02",
    "abyssPeriodId": 87700015,
    "levelList": [
      {
        "id": 20101212,
        "spinePosX": -55.0,
        "spinePosY": -300.0,
        "spineScale": 0.9
      },
      {
        "id": 20101215,
        "spinePosX": -55.0,
        "spinePosY": -300.0,
        "spineScale": 0.9
      }
    ],
    "firstPassAward": [],
    "firstPassAwardS": [],
    "timeStar": 720
  },
  {
    "id": 87600040,
    "idCN": "深渊/07期/深渊01",
    "mod": "默认",
    "isInformalData": false,
    "abyssName": "夺命三头龙·一",
    "abyssDes": "",
    "abyssIndex": "DT-01",
    "abyssPeriodId": 87700015,
    "levelList": [
      {
        "id": 20101213,
        "spinePosX": -55.0,
        "spinePosY": -300.0,
        "spineScale": 0.9
      },
      {
        "id": 20101214,
        "spinePosX": -55.0,
        "spinePosY": -300.0,
        "spineScale": 0.9
      }
    ],
    "firstPassAward": [],
    "firstPassAwardS": [],
    "timeStar": 720
  },
  {
    "id": 87600041,
    "idCN": "作战中心/汇流塔/关卡11",
    "mod": "默认",
    "isInformalData": false,
    "abyssName": "瞬息之梦",
    "abyssDes": "",
    "abyssIndex": "HL-11",
    "abyssPeriodId": -1,
    "levelList": [
      {
        "id": 20101217,
        "spinePosX": 0.0,
        "spinePosY": -320.0,
        "spineScale": 1.0
      },
      {
        "id": 20101218,
        "spinePosX": 0.0,
        "spinePosY": -180.0,
        "spineScale": 1.0
      }
    ],
    "firstPassAward": [],
    "firstPassAwardS": [],
    "timeStar": 720
  },
  {
    "id": 87600042,
    "idCN": "作战中心/汇流塔/关卡12",
    "mod": "默认",
    "isInformalData": false,
    "abyssName": "须臾之梦",
    "abyssDes": "",
    "abyssIndex": "HL-12",
    "abyssPeriodId": -1,
    "levelList": [
      {
        "id": 20101219,
        "spinePosX": 0.0,
        "spinePosY": -310.0,
        "spineScale": 1.0
      },
      {
        "id": 20101220,
        "spinePosX": 0.0,
        "spinePosY": -180.0,
        "spineScale": 1.0
      }
    ],
    "firstPassAward": [],
    "firstPassAwardS": [],
    "timeStar": 720
  },
  {
    "id": 87600043,
    "idCN": "作战中心/汇流塔/关卡13",
    "mod": "默认",
    "isInformalData": false,
    "abyssName": "紧握其剑",
    "abyssDes": "",
    "abyssIndex": "HL-13",
    "abyssPeriodId": -1,
    "levelList": [
      {
        "id": 20101222,
        "spinePosX": 0.0,
        "spinePosY": -180.0,
        "spineScale": 1.0
      },
      {
        "id": 20101223,
        "spinePosX": 0.0,
        "spinePosY": -180.0,
        "spineScale": 1.0
      }
    ],
    "firstPassAward": [],
    "firstPassAwardS": [],
    "timeStar": 720
  },
  {
    "id": 87600044,
    "idCN": "作战中心/汇流塔/关卡14",
    "mod": "默认",
    "isInformalData": false,
    "abyssName": "万钧试炼",
    "abyssDes": "",
    "abyssIndex": "HL-14",
    "abyssPeriodId": -1,
    "levelList": [
      {
        "id": 20101226,
        "spinePosX": 0.0,
        "spinePosY": -290.0,
        "spineScale": 0.9
      },
      {
        "id": 20101224,
        "spinePosX": 0.0,
        "spinePosY": -360.0,
        "spineScale": 1.0
      }
    ],
    "firstPassAward": [],
    "firstPassAwardS": [],
    "timeStar": 720
  },
  {
    "id": 87600045,
    "idCN": "作战中心/汇流塔/关卡15",
    "mod": "默认",
    "isInformalData": false,
    "abyssName": "万钧众仪",
    "abyssDes": "",
    "abyssIndex": "HL-15",
    "abyssPeriodId": -1,
    "levelList": [
      {
        "id": 20101227,
        "spinePosX": 0.0,
        "spinePosY": -310.0,
        "spineScale": 1.0
      },
      {
        "id": 20101225,
        "spinePosX": 0.0,
        "spinePosY": -290.0,
        "spineScale": 0.9
      }
    ],
    "firstPassAward": [],
    "firstPassAwardS": [],
    "timeStar": 720
  },
  {
    "id": 87600046,
    "idCN": "深渊/08期/深渊03",
    "mod": "默认",
    "isInformalData": false,
    "abyssName": "昔日梦境·三",
    "abyssDes": "",
    "abyssIndex": "PD-03",
    "abyssPeriodId": 87700020,
    "levelList": [
      {
        "id": 20101259,
        "spinePosX": 0.0,
        "spinePosY": -180.0,
        "spineScale": 1.0
      },
      {
        "id": 20101257,
        "spinePosX": 0.0,
        "spinePosY": -180.0,
        "spineScale": 1.0
      }
    ],
    "firstPassAward": [],
    "firstPassAwardS": [],
    "timeStar": 720
  },
  {
    "id": 87600047,
    "idCN": "深渊/08期/深渊04",
    "mod": "默认",
    "isInformalData": false,
    "abyssName": "昔日梦境·四",
    "abyssDes": "",
    "abyssIndex": "PD-04",
    "abyssPeriodId": 87700020,
    "levelList": [
      {
        "id": 20101262,
        "spinePosX": 0.0,
        "spinePosY": -180.0,
        "spineScale": 1.0
      },
      {
        "id": 20101263,
        "spinePosX": 0.0,
        "spinePosY": -180.0,
        "spineScale": 1.0
      }
    ],
    "firstPassAward": [],
    "firstPassAwardS": [],
    "timeStar": 720
  },
  {
    "id": 87600048,
    "idCN": "深渊/08期/深渊02",
    "mod": "默认",
    "isInformalData": false,
    "abyssName": "昔日梦境·二",
    "abyssDes": "",
    "abyssIndex": "PD-02",
    "abyssPeriodId": 87700020,
    "levelList": [
      {
        "id": 20101264,
        "spinePosX": 0.0,
        "spinePosY": -180.0,
        "spineScale": 1.0
      },
      {
        "id": 20101260,
        "spinePosX": 0.0,
        "spinePosY": -180.0,
        "spineScale": 1.0
      }
    ],
    "firstPassAward": [],
    "firstPassAwardS": [],
    "timeStar": 720
  },
  {
    "id": 87600049,
    "idCN": "深渊/08期/深渊01",
    "mod": "默认",
    "isInformalData": false,
    "abyssName": "昔日梦境·一",
    "abyssDes": "",
    "abyssIndex": "PD-01",
    "abyssPeriodId": 87700020,
    "levelList": [
      {
        "id": 20101261,
        "spinePosX": 0.0,
        "spinePosY": -180.0,
        "spineScale": 1.0
      },
      {
        "id": 20101258,
        "spinePosX": 0.0,
        "spinePosY": -180.0,
        "spineScale": 1.0
      }
    ],
    "firstPassAward": [],
    "firstPassAwardS": [],
    "timeStar": 720
  },
  {
    "id": 87600026,
    "idCN": "深渊/09期/深渊03",
    "mod": "默认",
    "isInformalData": false,
    "abyssName": "剑刃与扳机·三",
    "abyssDes": "",
    "abyssIndex": "ST-03",
    "abyssPeriodId": 87700021,
    "levelList": [
      {
        "id": 20101302,
        "spinePosX": 0.0,
        "spinePosY": -180.0,
        "spineScale": 0.9
      },
      {
        "id": 20101300,
        "spinePosX": 0.0,
        "spinePosY": -180.0,
        "spineScale": 0.9
      }
    ],
    "firstPassAward": [],
    "firstPassAwardS": [],
    "timeStar": 720
  },
  {
    "id": 87600050,
    "idCN": "深渊/09期/深渊01",
    "mod": "默认",
    "isInformalData": false,
    "abyssName": "剑刃与扳机·一",
    "abyssDes": "",
    "abyssIndex": "ST-01",
    "abyssPeriodId": 87700021,
    "levelList": [
      {
        "id": 20101295,
        "spinePosX": 0.0,
        "spinePosY": -180.0,
        "spineScale": 0.9
      },
      {
        "id": 20101296,
        "spinePosX": 0.0,
        "spinePosY": -180.0,
        "spineScale": 0.9
      }
    ],
    "firstPassAward": [],
    "firstPassAwardS": [],
    "timeStar": 720
  },
  {
    "id": 87600051,
    "idCN": "深渊/09期/深渊02",
    "mod": "默认",
    "isInformalData": false,
    "abyssName": "剑刃与扳机·二",
    "abyssDes": "",
    "abyssIndex": "ST-02",
    "abyssPeriodId": 87700021,
    "levelList": [
      {
        "id": 20101298,
        "spinePosX": 0.0,
        "spinePosY": -180.0,
        "spineScale": 0.9
      },
      {
        "id": 20101301,
        "spinePosX": 0.0,
        "spinePosY": -180.0,
        "spineScale": 0.9
      }
    ],
    "firstPassAward": [],
    "firstPassAwardS": [],
    "timeStar": 720
  },
  {
    "id": 87600052,
    "idCN": "深渊/09期/深渊04",
    "mod": "默认",
    "isInformalData": false,
    "abyssName": "剑刃与扳机·四",
    "abyssDes": "",
    "abyssIndex": "ST-04",
    "abyssPeriodId": 87700021,
    "levelList": [
      {
        "id": 20101299,
        "spinePosX": 0.0,
        "spinePosY": -180.0,
        "spineScale": 0.9
      },
      {
        "id": 20101297,
        "spinePosX": 0.0,
        "spinePosY": -180.0,
        "spineScale": 0.9
      }
    ],
    "firstPassAward": [],
    "firstPassAwardS": [],
    "timeStar": 720
  }
]