[
  {
    "id": 70200023,
    "idCN": "背景/七号自由港",
    "mod": "火车场景零件",
    "isInformalData": false,
    "path": "Environment/RN_Scenes/Map_Loading\\Loading_7FP/BG_7FP",
    "threeDPath": ""
  },
  {
    "id": 70200022,
    "idCN": "背景/修格里城",
    "mod": "火车场景零件",
    "isInformalData": false,
    "path": "Environment/RN_Scenes/Map_Loading\\Loading_XGLC/BG_XGLC",
    "threeDPath": ""
  },
  {
    "id": 70200024,
    "idCN": "背景/纯黑",
    "mod": "火车场景零件",
    "isInformalData": false,
    "path": "",
    "threeDPath": ""
  },
  {
    "id": 70200025,
    "idCN": "背景/C3",
    "mod": "火车场景零件",
    "isInformalData": false,
    "path": "",
    "threeDPath": ""
  },
  {
    "id": 70200026,
    "idCN": "C3/沙丘",
    "mod": "火车场景零件",
    "isInformalData": false,
    "path": "",
    "threeDPath": ""
  },
  {
    "id": 70200027,
    "idCN": "C3/楼1",
    "mod": "火车场景零件",
    "isInformalData": false,
    "path": "",
    "threeDPath": ""
  },
  {
    "id": 70200028,
    "idCN": "C3/楼2",
    "mod": "火车场景零件",
    "isInformalData": false,
    "path": "",
    "threeDPath": ""
  },
  {
    "id": 70200029,
    "idCN": "C3/楼3",
    "mod": "火车场景零件",
    "isInformalData": false,
    "path": "",
    "threeDPath": ""
  },
  {
    "id": 70200030,
    "idCN": "C3/楼4",
    "mod": "火车场景零件",
    "isInformalData": false,
    "path": "",
    "threeDPath": ""
  },
  {
    "id": 70200031,
    "idCN": "C3/楼5",
    "mod": "火车场景零件",
    "isInformalData": false,
    "path": "",
    "threeDPath": ""
  },
  {
    "id": 70200032,
    "idCN": "背景/曼德矿场",
    "mod": "火车场景零件",
    "isInformalData": false,
    "path": "Environment/RN_Scenes/Map_Loading/Loading_MD/BG_MD",
    "threeDPath": ""
  },
  {
    "id": 70200033,
    "idCN": "背景/荒原站",
    "mod": "火车场景零件",
    "isInformalData": false,
    "path": "Environment/RN_Scenes/Map_Loading\\Loading_HYZ/BG_HYZ_02",
    "threeDPath": ""
  },
  {
    "id": 70200035,
    "idCN": "背景/淘金乐园",
    "mod": "火车场景零件",
    "isInformalData": false,
    "path": "Environment/RN_Scenes/Map_Loading/Loading_TJLY/BG_TJLY",
    "threeDPath": ""
  },
  {
    "id": 70200034,
    "idCN": "背景/发电站",
    "mod": "火车场景零件",
    "isInformalData": false,
    "path": "Environment/RN_Scenes/Map_Loading\\Loading_FDZ/BG_FDZ",
    "threeDPath": ""
  },
  {
    "id": 70200036,
    "idCN": "背景/发射中心",
    "mod": "火车场景零件",
    "isInformalData": false,
    "path": "Environment/RN_Scenes/Map_Loading\\Loading_HJJD/BG_HJJD",
    "threeDPath": ""
  },
  {
    "id": 70200037,
    "idCN": "背景/澄明数据中心",
    "mod": "火车场景零件",
    "isInformalData": false,
    "path": "Environment/RN_Scenes/Map_Loading\\Loading_CMSJZX/BG_CMSJZX",
    "threeDPath": ""
  },
  {
    "id": 70200001,
    "idCN": "测试/Grass_C_Group_01",
    "mod": "火车场景零件",
    "isInformalData": false,
    "path": "",
    "threeDPath": "Environment/Prefab/Grass_C_Group_01"
  },
  {
    "id": 70200002,
    "idCN": "测试/Grass_C_Group_02",
    "mod": "火车场景零件",
    "isInformalData": false,
    "path": "",
    "threeDPath": "Environment/Prefab/Grass_C_Group_02"
  },
  {
    "id": 70200003,
    "idCN": "测试/Grass_C_Group_03",
    "mod": "火车场景零件",
    "isInformalData": false,
    "path": "",
    "threeDPath": "Environment/Prefab/Grass_C_Group_03"
  },
  {
    "id": 70200004,
    "idCN": "背景/阿妮塔战备工厂",
    "mod": "火车场景零件",
    "isInformalData": false,
    "path": "Environment/RN_Scenes/Map_Loading\\Loading_WQYJS/BG_WQYJS",
    "threeDPath": ""
  },
  {
    "id": 70200005,
    "idCN": "背景/荒原站无观测站",
    "mod": "火车场景零件",
    "isInformalData": false,
    "path": "Environment/RN_Scenes/Map_Loading\\Loading_HYZ/BG_HYZ_01",
    "threeDPath": ""
  },
  {
    "id": 70200006,
    "idCN": "背景/铁盟哨站",
    "mod": "火车场景零件",
    "isInformalData": false,
    "path": "Environment/RN_Scenes/Map_Loading\\Loading_TMSZ/BG_TMSZ",
    "threeDPath": ""
  },
  {
    "id": 70200007,
    "idCN": "背景/云岫桥",
    "mod": "火车场景零件",
    "isInformalData": false,
    "path": "Environment/RN_Scenes/Map_Loading\\Loading_YXQ/BG_YXQ",
    "threeDPath": ""
  },
  {
    "id": 70200008,
    "idCN": "背景/海角城",
    "mod": "火车场景零件",
    "isInformalData": false,
    "path": "Environment/RN_Scenes/Map_Loading/Loading_HJC/BG_HJC",
    "threeDPath": ""
  },
  {
    "id": 70200009,
    "idCN": "背景/汇流塔",
    "mod": "火车场景零件",
    "isInformalData": false,
    "path": "Environment/RN_Scenes/Map_Loading/Loading_HLT/BG_HLT",
    "threeDPath": ""
  }
]